<?xml version="1.0" encoding="UTF-8"?>
<ClinicalDocument xmlns="urn:hl7-org:v3" xmlns:sdtc="urn:hl7-org:sdtc" xmlns:xsi="http://www.w3.org/2001/XMLSchema-instance" xsi:schemaLocation="urn:hl7-org:v3 http://xreg2.nist.gov:8080/hitspValidation/schema/cdar2c32/infrastructure/cda/C32_CDA.xsd">
  <realmCode code="US"/>
  <typeId root="2.16.840.1.113883.1.3" extension="POCD_HD000040"/>
  <templateId root="2.16.840.1.113883.10.20.22.1.1" extension="2015-08-01"/>
  <templateId root="2.16.840.1.113883.10.20.22.1.2" extension="2015-08-01"/>
  <id root="2.16.840.1.113883.19.5" extension="cdc302e1-1148-467f-accd-0e3d6914b4d8" assigningAuthorityName="https://github.com/synthetichealth/synthea"/>
  <code code="34133-9" displayName="Summarization of episode note" codeSystem="2.16.840.1.113883.6.1" codeSystemName="LOINC"/>
  <title>C-CDA R2.1 Patient Record: Matilde468 Jakubowski832</title>
  <effectiveTime value="20190919185616"/>
  <confidentialityCode code="N"/>
  <languageCode code="en-US"/>
  <recordTarget>
    <patientRole>
      <id root="2.16.840.1.113883.19.5" extension="cdc302e1-1148-467f-accd-0e3d6914b4d8" assigningAuthorityName="https://github.com/synthetichealth/synthea"/>
      <addr use="HP">
        <streetAddressLine>1088 Abernathy Estate</streetAddressLine>
        <city>Brookline</city>
        <state>Massachusetts</state>
        <postalCode>02215</postalCode>
      </addr>
      <telecom nullFlavor="NI"/>
      <patient>
        <name>
          <given>Matilde468</given>
          <family>Jakubowski832</family>
        </name>
        <administrativeGenderCode code="F" codeSystem="2.16.840.1.113883.5.1" codeSystemName="HL7 AdministrativeGender"/>
        <birthTime value="20190718185616"/>
        <raceCode code="2106-3" displayName="white" codeSystemName="CDC Race and Ethnicity" codeSystem="2.16.840.1.113883.6.238"/>
        <ethnicGroupCode code="2186-5" displayName="non-hispanic" codeSystemName="CDC Race and Ethnicity" codeSystem="2.16.840.1.113883.6.238"/>
        <languageCommunication>
          <languageCode code="en-US"/>
        </languageCommunication>
      </patient>
    </patientRole>
  </recordTarget>
  <author>
    <time value="20190919185616"/>
    <assignedAuthor>
      <id nullFlavor="NA"/>
      <addr nullFlavor="NA" />
      <telecom nullFlavor="NA" />
      <assignedAuthoringDevice>
        <manufacturerModelName>https://github.com/synthetichealth/synthea</manufacturerModelName>
        <softwareName>https://github.com/synthetichealth/synthea</softwareName>
      </assignedAuthoringDevice>
      <representedOrganization>
        <id nullFlavor="NA"/>
        <name>PCP7947</name>
        <telecom nullFlavor="NA"/>
        <addr>
          <streetAddressLine>111 PERKINS ST</streetAddressLine>
          <city>JAMAICA PLAIN</city>
          <state>MA</state>
          <postalCode>02130-4323</postalCode>
        </addr>
      </representedOrganization>
    </assignedAuthor>
  </author>
  <custodian>
    <assignedCustodian>
      <representedCustodianOrganization>
        <id nullFlavor="NA"/>
        <name>PCP7947</name>
        <telecom nullFlavor="NA"/>
        <addr>
          <streetAddressLine>111 PERKINS ST</streetAddressLine>
          <city>JAMAICA PLAIN</city>
          <state>MA</state>
          <postalCode>02130-4323</postalCode>
        </addr>
      </representedCustodianOrganization>
    </assignedCustodian>
  </custodian>
  <documentationOf>
    <serviceEvent classCode="PCPR">
      <effectiveTime>
        <low value="20190718185616"/>
        <high value="20190919185616"/>
      </effectiveTime>
    </serviceEvent>
  </documentationOf>
  <component>
    <structuredBody>
<component>
  <!-- Allergies: patient has no allergies -->
  <section nullFlavor="NI">
    <templateId root="2.16.840.1.113883.10.20.22.2.6.1" extension="2015-08-01"/>
    <code code="48765-2" codeSystem="2.16.840.1.113883.6.1" codeSystemName="LOINC" displayName="Allergy List"/>
    <title>Allergies</title>                
    <text>There are no current allergies at the time of this document's creation.</text>
  </section>
</component><component>
  <!--Medications-->
  <section>
	<templateId root="2.16.840.1.113883.10.20.22.2.1.1" extension="2014-06-09"/>
    <code code="10160-0" displayName="History of medication use" codeSystem="2.16.840.1.113883.6.1" codeSystemName="LOINC"/>
    <title>Medications</title>
<text>
  <table border="1" width="100%">
    <thead>
      <tr>
        <th>Start</th>
        <th>Stop</th>
        <th>Description</th>
        <th>Code</th>
      </tr>
    </thead>
    <tbody>
        <tr>
          <td>2019-08-17T18:56:16-04:00</td>
          <td>2019-08-31T18:56:16-04:00</td>
          <td ID="medications-desc-1">Amoxicillin 250 MG Oral Capsule</td>
          <td ID="medications-code-1">RxNorm 308182</td>
        </tr>
        <tr>
          <td>2019-08-17T18:56:16-04:00</td>
          <td>2019-08-31T18:56:16-04:00</td>
          <td ID="medications-desc-2">Ibuprofen 100 MG Oral Tablet</td>
          <td ID="medications-code-2">RxNorm 198405</td>
        </tr>
    </tbody>
  </table>
</text>
    <entry>
      <!--CCD Medication activity - Required-->
      <substanceAdministration classCode="SBADM" moodCode="EVN">
        <templateId root="2.16.840.1.113883.10.20.22.4.16" extension="2014-06-09"/>
        <id root="639dba05-d779-416e-8ee8-865cf4a7ea2b"/>
        <statusCode code="completed"/>
        <effectiveTime xsi:type="IVL_TS">
          <low value="20190817185616"/>
          <high value="20190831185616"/>
        </effectiveTime>
        <doseQuantity value="1"/>
        <consumable>
          <!--CCD Product - Required-->
          <manufacturedProduct classCode="MANU">
            <templateId root="2.16.840.1.113883.10.20.22.4.23" extension="2014-06-09"/>
            <manufacturedMaterial>
        <code  code="308182" codeSystem="2.16.840.1.113883.6.88" displayName="Amoxicillin 250 MG Oral Capsule">
          <originalText><reference value="#medications-desc-1"/></originalText>
          <translation code="308182" codeSystem="2.16.840.1.113883.6.88" displayName="Amoxicillin 250 MG Oral Capsule"/>
        </code>
              <name>Amoxicillin 250 MG Oral Capsule</name>
            </manufacturedMaterial>
          </manufacturedProduct>
        </consumable>
      </substanceAdministration>
    </entry>
    <entry>
      <!--CCD Medication activity - Required-->
      <substanceAdministration classCode="SBADM" moodCode="EVN">
        <templateId root="2.16.840.1.113883.10.20.22.4.16" extension="2014-06-09"/>
        <id root="2393df65-78ba-408c-b1eb-ea6fc2c614d8"/>
        <statusCode code="completed"/>
        <effectiveTime xsi:type="IVL_TS">
          <low value="20190817185616"/>
          <high value="20190831185616"/>
        </effectiveTime>
        <doseQuantity value="1"/>
        <consumable>
          <!--CCD Product - Required-->
          <manufacturedProduct classCode="MANU">
            <templateId root="2.16.840.1.113883.10.20.22.4.23" extension="2014-06-09"/>
            <manufacturedMaterial>
        <code  code="198405" codeSystem="2.16.840.1.113883.6.88" displayName="Ibuprofen 100 MG Oral Tablet">
          <originalText><reference value="#medications-desc-2"/></originalText>
          <translation code="198405" codeSystem="2.16.840.1.113883.6.88" displayName="Ibuprofen 100 MG Oral Tablet"/>
        </code>
              <name>Ibuprofen 100 MG Oral Tablet</name>
            </manufacturedMaterial>
          </manufacturedProduct>
        </consumable>
      </substanceAdministration>
    </entry>
  </section>
</component>
<component>
  <!--Diagnostic Results-->
  <section>
    <templateId root="2.16.840.1.113883.10.20.22.2.3.1" extension="2015-08-01"/>
    <!--Diagnostic Results section template-->
    <code code="30954-2" codeSystem="2.16.840.1.113883.6.1" codeSystemName="LOINC" displayName="Results"/>
    <title>Diagnostic Results</title>
<text>
  <table border="1" width="100%">
    <thead>
      <tr>
        <th>Start</th>
        <th>Stop</th>
        <th>Description</th>
        <th>Code</th>
      </tr>
    </thead>
    <tbody>
        <tr>
          <td>2019-07-18T18:56:16-04:00</td>
          <td></td>
          <td ID="reports-desc-1">Complete blood count (hemogram) panel - Blood by Automated count</td>
          <td ID="reports-code-1">LOINC 58410-2</td>
        </tr>
    </tbody>
  </table>
</text>
    <entry typeCode="DRIV">
      <organizer classCode="BATTERY" moodCode="EVN">
        <templateId root="2.16.840.1.113883.10.20.22.4.1" extension="2015-08-01"/>
        <!--Result organizer template -->
        <id root="efdeba23-a7ee-43c1-a740-bc0025407b63"/>
        <code nullFlavor="NA"/>
        <statusCode code="completed"/>
        <effectiveTime>
          <low value="20190718185616"/>
          <high value="20190718185616"/>
        </effectiveTime>
        <component>
          <observation classCode="OBS" moodCode="EVN">
          <templateId root="2.16.840.1.113883.10.20.22.4.2" extension="2015-08-01"/>
            <id root="62a9edbd-21a1-481e-9393-f078aceabcd8"/>
        <code  code="6690-2" codeSystem="2.16.840.1.113883.6.1" displayName="Leukocytes [#/volume] in Blood by Automated count">
          <originalText><reference value="#reports-desc-1"/></originalText>
          <translation code="6690-2" codeSystem="2.16.840.1.113883.6.1" displayName="Leukocytes [#/volume] in Blood by Automated count"/>
        </code>
            <text>
              <reference value="#reports-desc-1"/>
            </text>
            <statusCode code="completed"/>
            <effectiveTime value="20190718185616"/>
            <value xsi:type="PQ" value="9.405819588426798" unit="10*3/uL"/>
          </observation>
        </component>
        <component>
          <observation classCode="OBS" moodCode="EVN">
          <templateId root="2.16.840.1.113883.10.20.22.4.2" extension="2015-08-01"/>
            <id root="f25cbf62-4b44-4518-88ac-58194626168b"/>
        <code  code="789-8" codeSystem="2.16.840.1.113883.6.1" displayName="Erythrocytes [#/volume] in Blood by Automated count">
          <originalText><reference value="#reports-desc-1"/></originalText>
          <translation code="789-8" codeSystem="2.16.840.1.113883.6.1" displayName="Erythrocytes [#/volume] in Blood by Automated count"/>
        </code>
            <text>
              <reference value="#reports-desc-1"/>
            </text>
            <statusCode code="completed"/>
            <effectiveTime value="20190718185616"/>
            <value xsi:type="PQ" value="3.931849666172433" unit="10*6/uL"/>
          </observation>
        </component>
        <component>
          <observation classCode="OBS" moodCode="EVN">
          <templateId root="2.16.840.1.113883.10.20.22.4.2" extension="2015-08-01"/>
            <id root="62cea27d-0bf2-4aed-aca2-e1e564ca4d1f"/>
        <code  code="718-7" codeSystem="2.16.840.1.113883.6.1" displayName="Hemoglobin [Mass/volume] in Blood">
          <originalText><reference value="#reports-desc-1"/></originalText>
          <translation code="718-7" codeSystem="2.16.840.1.113883.6.1" displayName="Hemoglobin [Mass/volume] in Blood"/>
        </code>
            <text>
              <reference value="#reports-desc-1"/>
            </text>
            <statusCode code="completed"/>
            <effectiveTime value="20190718185616"/>
            <value xsi:type="PQ" value="13.161888532087584" unit="g/dL"/>
          </observation>
        </component>
        <component>
          <observation classCode="OBS" moodCode="EVN">
          <templateId root="2.16.840.1.113883.10.20.22.4.2" extension="2015-08-01"/>
            <id root="08807cc7-0287-4c02-84df-c522188b6810"/>
        <code  code="4544-3" codeSystem="2.16.840.1.113883.6.1" displayName="Hematocrit [Volume Fraction] of Blood by Automated count">
          <originalText><reference value="#reports-desc-1"/></originalText>
          <translation code="4544-3" codeSystem="2.16.840.1.113883.6.1" displayName="Hematocrit [Volume Fraction] of Blood by Automated count"/>
        </code>
            <text>
              <reference value="#reports-desc-1"/>
            </text>
            <statusCode code="completed"/>
            <effectiveTime value="20190718185616"/>
            <value xsi:type="PQ" value="39.067094925099525" unit="%"/>
          </observation>
        </component>
        <component>
          <observation classCode="OBS" moodCode="EVN">
          <templateId root="2.16.840.1.113883.10.20.22.4.2" extension="2015-08-01"/>
            <id root="dc5f194b-fb16-49af-b595-2ec1a1e7583e"/>
        <code  code="787-2" codeSystem="2.16.840.1.113883.6.1" displayName="MCV [Entitic volume] by Automated count">
          <originalText><reference value="#reports-desc-1"/></originalText>
          <translation code="787-2" codeSystem="2.16.840.1.113883.6.1" displayName="MCV [Entitic volume] by Automated count"/>
        </code>
            <text>
              <reference value="#reports-desc-1"/>
            </text>
            <statusCode code="completed"/>
            <effectiveTime value="20190718185616"/>
            <value xsi:type="PQ" value="94.37057401846272" unit="fL"/>
          </observation>
        </component>
        <component>
          <observation classCode="OBS" moodCode="EVN">
          <templateId root="2.16.840.1.113883.10.20.22.4.2" extension="2015-08-01"/>
            <id root="18c99170-7b9f-4f70-bf34-788fb1838f62"/>
        <code  code="785-6" codeSystem="2.16.840.1.113883.6.1" displayName="MCH [Entitic mass] by Automated count">
          <originalText><reference value="#reports-desc-1"/></originalText>
          <translation code="785-6" codeSystem="2.16.840.1.113883.6.1" displayName="MCH [Entitic mass] by Automated count"/>
        </code>
            <text>
              <reference value="#reports-desc-1"/>
            </text>
            <statusCode code="completed"/>
            <effectiveTime value="20190718185616"/>
            <value xsi:type="PQ" value="32.70014146644685" unit="pg"/>
          </observation>
        </component>
        <component>
          <observation classCode="OBS" moodCode="EVN">
          <templateId root="2.16.840.1.113883.10.20.22.4.2" extension="2015-08-01"/>
            <id root="eccf6127-630d-40cd-af9b-295017442d7a"/>
        <code  code="786-4" codeSystem="2.16.840.1.113883.6.1" displayName="MCHC [Mass/volume] by Automated count">
          <originalText><reference value="#reports-desc-1"/></originalText>
          <translation code="786-4" codeSystem="2.16.840.1.113883.6.1" displayName="MCHC [Mass/volume] by Automated count"/>
        </code>
            <text>
              <reference value="#reports-desc-1"/>
            </text>
            <statusCode code="completed"/>
            <effectiveTime value="20190718185616"/>
            <value xsi:type="PQ" value="33.43788680960731" unit="g/dL"/>
          </observation>
        </component>
        <component>
          <observation classCode="OBS" moodCode="EVN">
          <templateId root="2.16.840.1.113883.10.20.22.4.2" extension="2015-08-01"/>
            <id root="3beed163-9213-4cb4-a3c3-46fa4e7ac62a"/>
        <code  code="21000-5" codeSystem="2.16.840.1.113883.6.1" displayName="Erythrocyte distribution width [Entitic volume] by Automated count">
          <originalText><reference value="#reports-desc-1"/></originalText>
          <translation code="21000-5" codeSystem="2.16.840.1.113883.6.1" displayName="Erythrocyte distribution width [Entitic volume] by Automated count"/>
        </code>
            <text>
              <reference value="#reports-desc-1"/>
            </text>
            <statusCode code="completed"/>
            <effectiveTime value="20190718185616"/>
            <value xsi:type="PQ" value="40.82547230044765" unit="fL"/>
          </observation>
        </component>
        <component>
          <observation classCode="OBS" moodCode="EVN">
          <templateId root="2.16.840.1.113883.10.20.22.4.2" extension="2015-08-01"/>
            <id root="d16cec3b-1641-4d5c-ad0d-e21d96468825"/>
        <code  code="777-3" codeSystem="2.16.840.1.113883.6.1" displayName="Platelets [#/volume] in Blood by Automated count">
          <originalText><reference value="#reports-desc-1"/></originalText>
          <translation code="777-3" codeSystem="2.16.840.1.113883.6.1" displayName="Platelets [#/volume] in Blood by Automated count"/>
        </code>
            <text>
              <reference value="#reports-desc-1"/>
            </text>
            <statusCode code="completed"/>
            <effectiveTime value="20190718185616"/>
            <value xsi:type="PQ" value="294.1232955490042" unit="10*3/uL"/>
          </observation>
        </component>
        <component>
          <observation classCode="OBS" moodCode="EVN">
          <templateId root="2.16.840.1.113883.10.20.22.4.2" extension="2015-08-01"/>
            <id root="bac756ef-7fb7-4197-9d2c-ad5be4ea2a5b"/>
        <code  code="32207-3" codeSystem="2.16.840.1.113883.6.1" displayName="Platelet distribution width [Entitic volume] in Blood by Automated count">
          <originalText><reference value="#reports-desc-1"/></originalText>
          <translation code="32207-3" codeSystem="2.16.840.1.113883.6.1" displayName="Platelet distribution width [Entitic volume] in Blood by Automated count"/>
        </code>
            <text>
              <reference value="#reports-desc-1"/>
            </text>
            <statusCode code="completed"/>
            <effectiveTime value="20190718185616"/>
            <value xsi:type="PQ" value="334.3211195095123" unit="fL"/>
          </observation>
        </component>
        <component>
          <observation classCode="OBS" moodCode="EVN">
          <templateId root="2.16.840.1.113883.10.20.22.4.2" extension="2015-08-01"/>
            <id root="816aa6f2-9857-4488-8099-3db783634168"/>
        <code  code="32623-1" codeSystem="2.16.840.1.113883.6.1" displayName="Platelet mean volume [Entitic volume] in Blood by Automated count">
          <originalText><reference value="#reports-desc-1"/></originalText>
          <translation code="32623-1" codeSystem="2.16.840.1.113883.6.1" displayName="Platelet mean volume [Entitic volume] in Blood by Automated count"/>
        </code>
            <text>
              <reference value="#reports-desc-1"/>
            </text>
            <statusCode code="completed"/>
            <effectiveTime value="20190718185616"/>
            <value xsi:type="PQ" value="10.348446013679476" unit="fL"/>
          </observation>
        </component>
      </organizer>
    </entry>
  </section>
</component>
<component>
  <!--Problems-->
  <section>
    <templateId root="2.16.840.1.113883.10.20.22.2.5.1" extension="2015-08-01"/>
    <!--Problems section template-->
    <code code="11450-4" codeSystem="2.16.840.1.113883.6.1" codeSystemName="LOINC" displayName="Problem list"/>
    <title>Problems</title>
<text>
  <table border="1" width="100%">
    <thead>
      <tr>
        <th>Start</th>
        <th>Stop</th>
        <th>Description</th>
        <th>Code</th>
      </tr>
    </thead>
    <tbody>
        <tr>
          <td>2019-08-17T18:56:16-04:00</td>
          <td></td>
          <td ID="conditions-desc-1">Otitis media</td>
          <td ID="conditions-code-1">SNOMED-CT 65363002</td>
        </tr>
    </tbody>
  </table>
</text>
    <entry typeCode="DRIV">
      <act classCode="ACT" moodCode="EVN">
        <templateId root="2.16.840.1.113883.10.20.22.4.3" extension="2015-08-01"/>
        <!-- Problem act template -->
        <id root="ee3608cb-aa74-40f5-8c32-ec69239b320d"/>
        <code nullFlavor="NA"/>
        <statusCode code="active"/>
        <effectiveTime>
          <low value="20190817185616"/>
          
        </effectiveTime>
        <entryRelationship typeCode="SUBJ" inversionInd="false">
          <observation classCode="OBS" moodCode="EVN">
            <templateId root="2.16.840.1.113883.10.20.22.4.4" extension="2015-08-01"/>
            <!--Problem observation template - NOT episode template-->
            <id root="9fbe9d5d-601d-40ca-a1f8-c361c08be273"/>
            <code code="64572001" displayName="Condition" codeSystem="2.16.840.1.113883.6.96" codeSystemName="SNOMED-CT">
              <translation code="75323-6" displayName="Condition" codeSystem="2.16.840.1.113883.6.1" codeSystemName="LOINC"/>
            </code>
            <text>
              <reference value="#conditions-desc-1"/>
            </text>
            <statusCode code="completed"/>
            <effectiveTime>
              <low value="20190817185616"/>
              
            </effectiveTime>
            <priorityCode code="8319008" codeSystem="2.16.840.1.113883.6.96" displayName="Principal diagnosis" />
        <value xsi:type="CD" code="65363002" codeSystem="2.16.840.1.113883.6.96" displayName="Otitis media">
          <originalText><reference value="#conditions-desc-1"/></originalText>
          <translation code="65363002" codeSystem="2.16.840.1.113883.6.96" displayName="Otitis media"/>
        </value>
          </observation>
        </entryRelationship>
      </act>
    </entry>
  </section>
</component>
<component>
  <!--Surgeries-->
  <section>
    <templateId root="2.16.840.1.113883.10.20.22.2.7.1" extension="2014-06-09"/>
    <!--Surgeries section template-->
    <code code="47519-4" codeSystem="2.16.840.1.113883.6.1" codeSystemName="LOINC" displayName="List of surgeries"/>
    <title>Surgeries</title>
<text>
  <table border="1" width="100%">
    <thead>
      <tr>
        <th>Start</th>
        <th>Stop</th>
        <th>Description</th>
        <th>Code</th>
      </tr>
    </thead>
    <tbody>
        <tr>
          <td>2019-07-18T18:56:16-04:00</td>
          <td>2019-07-18T19:11:16-04:00</td>
          <td ID="procedures-desc-1">Medication Reconciliation (procedure)</td>
          <td ID="procedures-code-1">SNOMED-CT 430193006</td>
        </tr>
    </tbody>
  </table>
</text>
    <entry typeCode="DRIV">
      <procedure classCode="PROC" moodCode="EVN">
        <templateId root="2.16.840.1.113883.10.20.22.4.14"/>
        <!-- Procedure activity template -->
        <id root="accdfa8b-a309-4dfb-bc32-791e6b1d559b"/>
        <code  code="430193006" codeSystem="2.16.840.1.113883.6.96" displayName="Medication Reconciliation (procedure)">
          <originalText><reference value="#procedures-desc-1"/></originalText>
          <translation code="430193006" codeSystem="2.16.840.1.113883.6.96" displayName="Medication Reconciliation (procedure)"/>
        </code>
        <text>
          <reference value="#procedures-desc-1"/>
        </text>
        <statusCode code="completed"/>
        <effectiveTime value="20190718185616"/>
      </procedure>
    </entry>
  </section>
</component>
<component>
  <!--Encounters-->
  <section>
    <templateId root="2.16.840.1.113883.10.20.22.2.22" extension="2015-08-01"/> <!-- CCDA Template id -->
    <!--Encounters section template-->
    <code code="46240-8" codeSystem="2.16.840.1.113883.6.1" codeSystemName="LOINC" displayName="History of encounters"/>
    <title>Encounters</title>
<text>
  <table border="1" width="100%">
    <thead>
      <tr>
        <th>Start</th>
        <th>Stop</th>
        <th>Description</th>
        <th>Code</th>
      </tr>
    </thead>
    <tbody>
        <tr>
          <td>2019-07-18T18:56:16-04:00</td>
          <td>2019-07-18T19:26:16-04:00</td>
          <td ID="encounters-desc-1">Well child visit (procedure)</td>
          <td ID="encounters-code-1">SNOMED-CT 410620009</td>
        </tr>
        <tr>
          <td>2019-08-22T18:56:16-04:00</td>
          <td>2019-08-22T19:11:16-04:00</td>
          <td ID="encounters-desc-2">Well child visit (procedure)</td>
          <td ID="encounters-code-2">SNOMED-CT 410620009</td>
        </tr>
        <tr>
          <td>2019-08-17T18:56:16-04:00</td>
          <td>2019-08-17T19:11:16-04:00</td>
          <td ID="encounters-desc-3">Encounter for symptom</td>
          <td ID="encounters-code-3">SNOMED-CT 185345009</td>
        </tr>
    </tbody>
  </table>
</text>
    <entry typeCode="DRIV">
      <encounter classCode="ENC" moodCode="EVN">
		    <templateId root="2.16.840.1.113883.10.20.22.4.49"/>
        <!-- Encounter activity template -->
        <id root="a76599d1-5f64-4ed6-a73c-4ff446f801db"/>
        <code  code="410620009" codeSystem="2.16.840.1.113883.6.96" displayName="Well child visit (procedure)">
          <originalText><reference value="#encounters-desc-1"/></originalText>
          <translation code="410620009" codeSystem="2.16.840.1.113883.6.96" displayName="Well child visit (procedure)"/>
        </code>
        <text>
          <reference value="#encounters-desc-1"/>
        </text>
        <effectiveTime>
          <low value="20190718185616"/>
          <high value="20190718192616"/>
        </effectiveTime>
      </encounter>
    </entry>
    <entry typeCode="DRIV">
      <encounter classCode="ENC" moodCode="EVN">
		    <templateId root="2.16.840.1.113883.10.20.22.4.49"/>
        <!-- Encounter activity template -->
        <id root="35d447b3-cf92-4aa3-8b34-a8c1ee87f814"/>
        <code  code="410620009" codeSystem="2.16.840.1.113883.6.96" displayName="Well child visit (procedure)">
          <originalText><reference value="#encounters-desc-2"/></originalText>
          <translation code="410620009" codeSystem="2.16.840.1.113883.6.96" displayName="Well child visit (procedure)"/>
        </code>
        <text>
          <reference value="#encounters-desc-2"/>
        </text>
        <effectiveTime>
          <low value="20190822185616"/>
          <high value="20190822191116"/>
        </effectiveTime>
      </encounter>
    </entry>
    <entry typeCode="DRIV">
      <encounter classCode="ENC" moodCode="EVN">
		    <templateId root="2.16.840.1.113883.10.20.22.4.49"/>
        <!-- Encounter activity template -->
        <id root="c81dfc2a-dc43-42f4-8fa7-3c7b32b7cab3"/>
        <code  code="185345009" codeSystem="2.16.840.1.113883.6.96" displayName="Encounter for symptom">
          <originalText><reference value="#encounters-desc-3"/></originalText>
          <translation code="185345009" codeSystem="2.16.840.1.113883.6.96" displayName="Encounter for symptom"/>
        </code>
        <text>
          <reference value="#encounters-desc-3"/>
        </text>
        <effectiveTime>
          <low value="20190817185616"/>
          <high value="20190817191116"/>
        </effectiveTime>
      </encounter>
    </entry>
  </section>
</component>
<component>
  <!--Vital Signs-->
  <section>
    <templateId root="2.16.840.1.113883.10.20.22.2.4.1" extension="2015-08-01"/>
    <!--Vital Signs section template-->
    <code code="8716-3" codeSystem="2.16.840.1.113883.6.1" codeSystemName="LOINC" displayName="Vital signs"/>
    <title>Vital Signs</title>
<text>
  <table border="1" width="100%">
    <thead>
      <tr>
        <th>Start</th>
        <th>Stop</th>
        <th>Description</th>
        <th>Code</th>
        <th>Value</th>
      </tr>
    </thead>
    <tbody>
        <tr>
          <td>2019-07-18T18:56:16-04:00</td>
          <td></td>
          <td ID="observations-desc-1">Body Height</td>
          <td ID="observations-code-1">LOINC 8302-2</td>
          <td>54.50182523559347 cm</td>
        </tr>
        <tr>
          <td>2019-07-18T18:56:16-04:00</td>
          <td></td>
          <td ID="observations-desc-2">Pain severity - 0-10 verbal numeric rating [Score] - Reported</td>
          <td ID="observations-code-2">LOINC 72514-3</td>
          <td>1.9510783933211284 {score}</td>
        </tr>
        <tr>
          <td>2019-07-18T18:56:16-04:00</td>
          <td></td>
          <td ID="observations-desc-3">Body Weight</td>
          <td ID="observations-code-3">LOINC 29463-7</td>
          <td>3.195095357322083 kg</td>
        </tr>
        <tr>
          <td>2019-07-18T18:56:16-04:00</td>
          <td></td>
          <td ID="observations-desc-4">Weight-for-length Per age and sex</td>
          <td ID="observations-code-4">LOINC 77606-2</td>
          <td>0.0000334439044261 %</td>
        </tr>
        <tr>
          <td>2019-07-18T18:56:16-04:00</td>
          <td></td>
          <td ID="observations-desc-5">Blood Pressure</td>
          <td ID="observations-code-5">LOINC 55284-4</td>
          <td>
          Diastolic Blood Pressure 83.61283567549714 mm[Hg]
          Systolic Blood Pressure 122.33634243187227 mm[Hg]
          </td>
        </tr>
        <tr>
          <td>2019-07-18T18:56:16-04:00</td>
          <td></td>
          <td ID="observations-desc-6">Leukocytes [#/volume] in Blood by Automated count</td>
          <td ID="observations-code-6">LOINC 6690-2</td>
          <td>9.405819588426798 10*3/uL</td>
        </tr>
        <tr>
          <td>2019-07-18T18:56:16-04:00</td>
          <td></td>
          <td ID="observations-desc-7">Erythrocytes [#/volume] in Blood by Automated count</td>
          <td ID="observations-code-7">LOINC 789-8</td>
          <td>3.931849666172433 10*6/uL</td>
        </tr>
        <tr>
          <td>2019-07-18T18:56:16-04:00</td>
          <td></td>
          <td ID="observations-desc-8">Hemoglobin [Mass/volume] in Blood</td>
          <td ID="observations-code-8">LOINC 718-7</td>
          <td>13.161888532087584 g/dL</td>
        </tr>
        <tr>
          <td>2019-07-18T18:56:16-04:00</td>
          <td></td>
          <td ID="observations-desc-9">Hematocrit [Volume Fraction] of Blood by Automated count</td>
          <td ID="observations-code-9">LOINC 4544-3</td>
          <td>39.067094925099525 %</td>
        </tr>
        <tr>
          <td>2019-07-18T18:56:16-04:00</td>
          <td></td>
          <td ID="observations-desc-10">MCV [Entitic volume] by Automated count</td>
          <td ID="observations-code-10">LOINC 787-2</td>
          <td>94.37057401846272 fL</td>
        </tr>
        <tr>
          <td>2019-07-18T18:56:16-04:00</td>
          <td></td>
          <td ID="observations-desc-11">MCH [Entitic mass] by Automated count</td>
          <td ID="observations-code-11">LOINC 785-6</td>
          <td>32.70014146644685 pg</td>
        </tr>
        <tr>
          <td>2019-07-18T18:56:16-04:00</td>
          <td></td>
          <td ID="observations-desc-12">MCHC [Mass/volume] by Automated count</td>
          <td ID="observations-code-12">LOINC 786-4</td>
          <td>33.43788680960731 g/dL</td>
        </tr>
        <tr>
          <td>2019-07-18T18:56:16-04:00</td>
          <td></td>
          <td ID="observations-desc-13">Erythrocyte distribution width [Entitic volume] by Automated count</td>
          <td ID="observations-code-13">LOINC 21000-5</td>
          <td>40.82547230044765 fL</td>
        </tr>
        <tr>
          <td>2019-07-18T18:56:16-04:00</td>
          <td></td>
          <td ID="observations-desc-14">Platelets [#/volume] in Blood by Automated count</td>
          <td ID="observations-code-14">LOINC 777-3</td>
          <td>294.1232955490042 10*3/uL</td>
        </tr>
        <tr>
          <td>2019-07-18T18:56:16-04:00</td>
          <td></td>
          <td ID="observations-desc-15">Platelet distribution width [Entitic volume] in Blood by Automated count</td>
          <td ID="observations-code-15">LOINC 32207-3</td>
          <td>334.3211195095123 fL</td>
        </tr>
        <tr>
          <td>2019-07-18T18:56:16-04:00</td>
          <td></td>
          <td ID="observations-desc-16">Platelet mean volume [Entitic volume] in Blood by Automated count</td>
          <td ID="observations-code-16">LOINC 32623-1</td>
          <td>10.348446013679476 fL</td>
        </tr>
        <tr>
          <td>2019-07-18T18:56:16-04:00</td>
          <td></td>
          <td ID="observations-desc-17">Tobacco smoking status NHIS</td>
          <td ID="observations-code-17">LOINC 72166-2</td>
          <td>SNOMED-CT 266919005 Never smoker </td>
        </tr>
        <tr>
          <td>2019-08-22T18:56:16-04:00</td>
          <td></td>
          <td ID="observations-desc-18">Body Height</td>
          <td ID="observations-code-18">LOINC 8302-2</td>
          <td>58.020989382643194 cm</td>
        </tr>
        <tr>
          <td>2019-08-22T18:56:16-04:00</td>
          <td></td>
          <td ID="observations-desc-19">Pain severity - 0-10 verbal numeric rating [Score] - Reported</td>
          <td ID="observations-code-19">LOINC 72514-3</td>
          <td>0.1712335111552692 {score}</td>
        </tr>
        <tr>
          <td>2019-08-22T18:56:16-04:00</td>
          <td></td>
          <td ID="observations-desc-20">Body Weight</td>
          <td ID="observations-code-20">LOINC 29463-7</td>
          <td>3.8716454824715187 kg</td>
        </tr>
        <tr>
          <td>2019-08-22T18:56:16-04:00</td>
          <td></td>
          <td ID="observations-desc-21">Weight-for-length Per age and sex</td>
          <td ID="observations-code-21">LOINC 77606-2</td>
          <td>0.0000967033934186 %</td>
        </tr>
        <tr>
          <td>2019-08-22T18:56:16-04:00</td>
          <td></td>
          <td ID="observations-desc-22">Blood Pressure</td>
          <td ID="observations-code-22">LOINC 55284-4</td>
          <td>
          Diastolic Blood Pressure 75.77562511387183 mm[Hg]
          Systolic Blood Pressure 112.06334606714353 mm[Hg]
          </td>
        </tr>
        <tr>
          <td>2019-08-22T18:56:16-04:00</td>
          <td></td>
          <td ID="observations-desc-23">Tobacco smoking status NHIS</td>
          <td ID="observations-code-23">LOINC 72166-2</td>
          <td>SNOMED-CT 266919005 Never smoker </td>
        </tr>
    </tbody>
  </table>
</text>
    <entry typeCode="DRIV">
      <organizer classCode="CLUSTER" moodCode="EVN">
        <templateId root="2.16.840.1.113883.10.20.22.4.26" extension="2015-08-01"/>
        <!-- Vital signs organizer template -->
        <id root="0c9f66fc-b178-460c-a44b-fcaf7becef0a"/>
        <code code="46680005" codeSystem="2.16.840.1.113883.6.96" displayName="Vital signs" codeSystemName="SNOMED CT">
          <translation code="74728-7" displayName="Vital signs, weight, height, head circumference, oximetry, BMI, and BSA panel" codeSystem="2.16.840.1.113883.6.1" codeSystemName="LOINC" />
        </code>
        <statusCode code="completed"/>
        <effectiveTime value="20190919185616"/>
        <component>
          <observation classCode="OBS" moodCode="EVN">
            <templateId root="2.16.840.1.113883.10.20.22.4.27" extension="2014-06-09"/>
            <!-- Result observation template -->
            <id root="6f1d1955-7dc0-4ffb-8f1f-4c989b14491c"/>
        <code  code="8302-2" codeSystem="2.16.840.1.113883.6.1" displayName="Body Height">
          <originalText><reference value="#observations-desc-1"/></originalText>
          <translation code="8302-2" codeSystem="2.16.840.1.113883.6.1" displayName="Body Height"/>
        </code>
            <text>
              <reference value="#observations-desc-1"/>
            </text>
            <statusCode code="completed"/>
            <effectiveTime value="20190718185616"/>
            <value xsi:type="PQ" value="54.50182523559347" unit="cm"/>
          </observation>
        </component>
        <component>
          <observation classCode="OBS" moodCode="EVN">
            <templateId root="2.16.840.1.113883.10.20.22.4.27" extension="2014-06-09"/>
            <!-- Result observation template -->
            <id root="c0e48219-4bd3-43b1-84f3-d80b81a5af94"/>
        <code  code="72514-3" codeSystem="2.16.840.1.113883.6.1" displayName="Pain severity - 0-10 verbal numeric rating [Score] - Reported">
          <originalText><reference value="#observations-desc-2"/></originalText>
          <translation code="72514-3" codeSystem="2.16.840.1.113883.6.1" displayName="Pain severity - 0-10 verbal numeric rating [Score] - Reported"/>
        </code>
            <text>
              <reference value="#observations-desc-2"/>
            </text>
            <statusCode code="completed"/>
            <effectiveTime value="20190718185616"/>
            <value xsi:type="PQ" value="1.9510783933211284" unit="{score}"/>
          </observation>
        </component>
        <component>
          <observation classCode="OBS" moodCode="EVN">
            <templateId root="2.16.840.1.113883.10.20.22.4.27" extension="2014-06-09"/>
            <!-- Result observation template -->
            <id root="ab4d9208-ec0b-46b7-af23-ca0d26a08ee3"/>
        <code  code="29463-7" codeSystem="2.16.840.1.113883.6.1" displayName="Body Weight">
          <originalText><reference value="#observations-desc-3"/></originalText>
          <translation code="29463-7" codeSystem="2.16.840.1.113883.6.1" displayName="Body Weight"/>
        </code>
            <text>
              <reference value="#observations-desc-3"/>
            </text>
            <statusCode code="completed"/>
            <effectiveTime value="20190718185616"/>
            <value xsi:type="PQ" value="3.195095357322083" unit="kg"/>
          </observation>
        </component>
        <component>
          <observation classCode="OBS" moodCode="EVN">
            <templateId root="2.16.840.1.113883.10.20.22.4.27" extension="2014-06-09"/>
            <!-- Result observation template -->
            <id root="69e661bc-3ec9-42e0-8cce-0bd8da71d1af"/>
        <code  code="77606-2" codeSystem="2.16.840.1.113883.6.1" displayName="Weight-for-length Per age and sex">
          <originalText><reference value="#observations-desc-4"/></originalText>
          <translation code="77606-2" codeSystem="2.16.840.1.113883.6.1" displayName="Weight-for-length Per age and sex"/>
        </code>
            <text>
              <reference value="#observations-desc-4"/>
            </text>
            <statusCode code="completed"/>
            <effectiveTime value="20190718185616"/>
            <value xsi:type="PQ" value="0.0000334439044261" unit="%"/>
          </observation>
        </component>
        <component>
          <observation classCode="OBS" moodCode="EVN">
            <templateId root="2.16.840.1.113883.10.20.22.4.27" extension="2014-06-09"/>
            <!-- Result observation template -->
            <id root="cd5024a7-8c8b-4812-99f2-6d660b4d1f78"/>
        <code  code="8462-4" codeSystem="2.16.840.1.113883.6.1" displayName="Diastolic Blood Pressure">
          <originalText><reference value="#observations-desc-5"/></originalText>
          <translation code="8462-4" codeSystem="2.16.840.1.113883.6.1" displayName="Diastolic Blood Pressure"/>
        </code>
            <text>
              <reference value="#observations-desc-5"/>
            </text>
            <statusCode code="completed"/>
            <effectiveTime value="20190718185616"/>
            <value xsi:type="PQ" value="83.61283567549714" unit="mm[Hg]"/>
          </observation>
        </component>
        <component>
          <observation classCode="OBS" moodCode="EVN">
            <templateId root="2.16.840.1.113883.10.20.22.4.27" extension="2014-06-09"/>
            <!-- Result observation template -->
            <id root="6fd765bf-0846-49e2-b645-74c129e5973b"/>
        <code  code="8480-6" codeSystem="2.16.840.1.113883.6.1" displayName="Systolic Blood Pressure">
          <originalText><reference value="#observations-desc-5"/></originalText>
          <translation code="8480-6" codeSystem="2.16.840.1.113883.6.1" displayName="Systolic Blood Pressure"/>
        </code>
            <text>
              <reference value="#observations-desc-5"/>
            </text>
            <statusCode code="completed"/>
            <effectiveTime value="20190718185616"/>
            <value xsi:type="PQ" value="122.33634243187227" unit="mm[Hg]"/>
          </observation>
        </component>
        <component>
          <observation classCode="OBS" moodCode="EVN">
            <templateId root="2.16.840.1.113883.10.20.22.4.27" extension="2014-06-09"/>
            <!-- Result observation template -->
            <id root="5cc3dd85-cd01-40d8-9f49-f0665a442d07"/>
        <code  code="6690-2" codeSystem="2.16.840.1.113883.6.1" displayName="Leukocytes [#/volume] in Blood by Automated count">
          <originalText><reference value="#observations-desc-6"/></originalText>
          <translation code="6690-2" codeSystem="2.16.840.1.113883.6.1" displayName="Leukocytes [#/volume] in Blood by Automated count"/>
        </code>
            <text>
              <reference value="#observations-desc-6"/>
            </text>
            <statusCode code="completed"/>
            <effectiveTime value="20190718185616"/>
            <value xsi:type="PQ" value="9.405819588426798" unit="10*3/uL"/>
          </observation>
        </component>
        <component>
          <observation classCode="OBS" moodCode="EVN">
            <templateId root="2.16.840.1.113883.10.20.22.4.27" extension="2014-06-09"/>
            <!-- Result observation template -->
            <id root="388ff7f9-00e0-4034-a19a-38d2aaca5090"/>
        <code  code="789-8" codeSystem="2.16.840.1.113883.6.1" displayName="Erythrocytes [#/volume] in Blood by Automated count">
          <originalText><reference value="#observations-desc-7"/></originalText>
          <translation code="789-8" codeSystem="2.16.840.1.113883.6.1" displayName="Erythrocytes [#/volume] in Blood by Automated count"/>
        </code>
            <text>
              <reference value="#observations-desc-7"/>
            </text>
            <statusCode code="completed"/>
            <effectiveTime value="20190718185616"/>
            <value xsi:type="PQ" value="3.931849666172433" unit="10*6/uL"/>
          </observation>
        </component>
        <component>
          <observation classCode="OBS" moodCode="EVN">
            <templateId root="2.16.840.1.113883.10.20.22.4.27" extension="2014-06-09"/>
            <!-- Result observation template -->
            <id root="93d8cab0-95c1-4bf8-a42e-ded586f070a6"/>
        <code  code="718-7" codeSystem="2.16.840.1.113883.6.1" displayName="Hemoglobin [Mass/volume] in Blood">
          <originalText><reference value="#observations-desc-8"/></originalText>
          <translation code="718-7" codeSystem="2.16.840.1.113883.6.1" displayName="Hemoglobin [Mass/volume] in Blood"/>
        </code>
            <text>
              <reference value="#observations-desc-8"/>
            </text>
            <statusCode code="completed"/>
            <effectiveTime value="20190718185616"/>
            <value xsi:type="PQ" value="13.161888532087584" unit="g/dL"/>
          </observation>
        </component>
        <component>
          <observation classCode="OBS" moodCode="EVN">
            <templateId root="2.16.840.1.113883.10.20.22.4.27" extension="2014-06-09"/>
            <!-- Result observation template -->
            <id root="f4430f6b-012a-4d04-88ff-cea53aecd583"/>
        <code  code="4544-3" codeSystem="2.16.840.1.113883.6.1" displayName="Hematocrit [Volume Fraction] of Blood by Automated count">
          <originalText><reference value="#observations-desc-9"/></originalText>
          <translation code="4544-3" codeSystem="2.16.840.1.113883.6.1" displayName="Hematocrit [Volume Fraction] of Blood by Automated count"/>
        </code>
            <text>
              <reference value="#observations-desc-9"/>
            </text>
            <statusCode code="completed"/>
            <effectiveTime value="20190718185616"/>
            <value xsi:type="PQ" value="39.067094925099525" unit="%"/>
          </observation>
        </component>
        <component>
          <observation classCode="OBS" moodCode="EVN">
            <templateId root="2.16.840.1.113883.10.20.22.4.27" extension="2014-06-09"/>
            <!-- Result observation template -->
            <id root="1669b20c-9112-413e-ae00-8277bfecab93"/>
        <code  code="787-2" codeSystem="2.16.840.1.113883.6.1" displayName="MCV [Entitic volume] by Automated count">
          <originalText><reference value="#observations-desc-10"/></originalText>
          <translation code="787-2" codeSystem="2.16.840.1.113883.6.1" displayName="MCV [Entitic volume] by Automated count"/>
        </code>
            <text>
              <reference value="#observations-desc-10"/>
            </text>
            <statusCode code="completed"/>
            <effectiveTime value="20190718185616"/>
            <value xsi:type="PQ" value="94.37057401846272" unit="fL"/>
          </observation>
        </component>
        <component>
          <observation classCode="OBS" moodCode="EVN">
            <templateId root="2.16.840.1.113883.10.20.22.4.27" extension="2014-06-09"/>
            <!-- Result observation template -->
            <id root="d1eb287e-f1d1-4fa0-835e-84229c8dfc86"/>
        <code  code="785-6" codeSystem="2.16.840.1.113883.6.1" displayName="MCH [Entitic mass] by Automated count">
          <originalText><reference value="#observations-desc-11"/></originalText>
          <translation code="785-6" codeSystem="2.16.840.1.113883.6.1" displayName="MCH [Entitic mass] by Automated count"/>
        </code>
            <text>
              <reference value="#observations-desc-11"/>
            </text>
            <statusCode code="completed"/>
            <effectiveTime value="20190718185616"/>
            <value xsi:type="PQ" value="32.70014146644685" unit="pg"/>
          </observation>
        </component>
        <component>
          <observation classCode="OBS" moodCode="EVN">
            <templateId root="2.16.840.1.113883.10.20.22.4.27" extension="2014-06-09"/>
            <!-- Result observation template -->
            <id root="e59414f3-4744-4818-9810-39944c62a1cc"/>
        <code  code="786-4" codeSystem="2.16.840.1.113883.6.1" displayName="MCHC [Mass/volume] by Automated count">
          <originalText><reference value="#observations-desc-12"/></originalText>
          <translation code="786-4" codeSystem="2.16.840.1.113883.6.1" displayName="MCHC [Mass/volume] by Automated count"/>
        </code>
            <text>
              <reference value="#observations-desc-12"/>
            </text>
            <statusCode code="completed"/>
            <effectiveTime value="20190718185616"/>
            <value xsi:type="PQ" value="33.43788680960731" unit="g/dL"/>
          </observation>
        </component>
        <component>
          <observation classCode="OBS" moodCode="EVN">
            <templateId root="2.16.840.1.113883.10.20.22.4.27" extension="2014-06-09"/>
            <!-- Result observation template -->
            <id root="c84866ab-9269-46d2-bbcf-2a331c81f2d8"/>
        <code  code="21000-5" codeSystem="2.16.840.1.113883.6.1" displayName="Erythrocyte distribution width [Entitic volume] by Automated count">
          <originalText><reference value="#observations-desc-13"/></originalText>
          <translation code="21000-5" codeSystem="2.16.840.1.113883.6.1" displayName="Erythrocyte distribution width [Entitic volume] by Automated count"/>
        </code>
            <text>
              <reference value="#observations-desc-13"/>
            </text>
            <statusCode code="completed"/>
            <effectiveTime value="20190718185616"/>
            <value xsi:type="PQ" value="40.82547230044765" unit="fL"/>
          </observation>
        </component>
        <component>
          <observation classCode="OBS" moodCode="EVN">
            <templateId root="2.16.840.1.113883.10.20.22.4.27" extension="2014-06-09"/>
            <!-- Result observation template -->
            <id root="c7d65f7a-e8ac-4d2c-9a51-462b6145eefa"/>
        <code  code="777-3" codeSystem="2.16.840.1.113883.6.1" displayName="Platelets [#/volume] in Blood by Automated count">
          <originalText><reference value="#observations-desc-14"/></originalText>
          <translation code="777-3" codeSystem="2.16.840.1.113883.6.1" displayName="Platelets [#/volume] in Blood by Automated count"/>
        </code>
            <text>
              <reference value="#observations-desc-14"/>
            </text>
            <statusCode code="completed"/>
            <effectiveTime value="20190718185616"/>
            <value xsi:type="PQ" value="294.1232955490042" unit="10*3/uL"/>
          </observation>
        </component>
        <component>
          <observation classCode="OBS" moodCode="EVN">
            <templateId root="2.16.840.1.113883.10.20.22.4.27" extension="2014-06-09"/>
            <!-- Result observation template -->
            <id root="cedf83d2-b5ed-4b29-921f-4d8dde3fc0f9"/>
        <code  code="32207-3" codeSystem="2.16.840.1.113883.6.1" displayName="Platelet distribution width [Entitic volume] in Blood by Automated count">
          <originalText><reference value="#observations-desc-15"/></originalText>
          <translation code="32207-3" codeSystem="2.16.840.1.113883.6.1" displayName="Platelet distribution width [Entitic volume] in Blood by Automated count"/>
        </code>
            <text>
              <reference value="#observations-desc-15"/>
            </text>
            <statusCode code="completed"/>
            <effectiveTime value="20190718185616"/>
            <value xsi:type="PQ" value="334.3211195095123" unit="fL"/>
          </observation>
        </component>
        <component>
          <observation classCode="OBS" moodCode="EVN">
            <templateId root="2.16.840.1.113883.10.20.22.4.27" extension="2014-06-09"/>
            <!-- Result observation template -->
            <id root="936bf785-eb41-45ee-bb85-caf368839835"/>
        <code  code="32623-1" codeSystem="2.16.840.1.113883.6.1" displayName="Platelet mean volume [Entitic volume] in Blood by Automated count">
          <originalText><reference value="#observations-desc-16"/></originalText>
          <translation code="32623-1" codeSystem="2.16.840.1.113883.6.1" displayName="Platelet mean volume [Entitic volume] in Blood by Automated count"/>
        </code>
            <text>
              <reference value="#observations-desc-16"/>
            </text>
            <statusCode code="completed"/>
            <effectiveTime value="20190718185616"/>
            <value xsi:type="PQ" value="10.348446013679476" unit="fL"/>
          </observation>
        </component>
        <component>
          <observation classCode="OBS" moodCode="EVN">
            <templateId root="2.16.840.1.113883.10.20.22.4.27" extension="2014-06-09"/>
            <!-- Result observation template -->
            <id root="b649e774-88db-4ff0-8e33-e1cedc1eecca"/>
        <code  code="72166-2" codeSystem="2.16.840.1.113883.6.1" displayName="Tobacco smoking status NHIS">
          <originalText><reference value="#observations-desc-17"/></originalText>
          <translation code="72166-2" codeSystem="2.16.840.1.113883.6.1" displayName="Tobacco smoking status NHIS"/>
        </code>
            <text>
              <reference value="#observations-desc-17"/>
            </text>
            <statusCode code="completed"/>
            <effectiveTime value="20190718185616"/>
            <value xsi:type="ST">SNOMED-CT 266919005 Never smoker</value>
          </observation>
        </component>
        <component>
          <observation classCode="OBS" moodCode="EVN">
            <templateId root="2.16.840.1.113883.10.20.22.4.27" extension="2014-06-09"/>
            <!-- Result observation template -->
            <id root="9c0a23ab-5387-4359-8ed5-3ebe92bcff6e"/>
        <code  code="8302-2" codeSystem="2.16.840.1.113883.6.1" displayName="Body Height">
          <originalText><reference value="#observations-desc-18"/></originalText>
          <translation code="8302-2" codeSystem="2.16.840.1.113883.6.1" displayName="Body Height"/>
        </code>
            <text>
              <reference value="#observations-desc-18"/>
            </text>
            <statusCode code="completed"/>
            <effectiveTime value="20190822185616"/>
            <value xsi:type="PQ" value="58.020989382643194" unit="cm"/>
          </observation>
        </component>
        <component>
          <observation classCode="OBS" moodCode="EVN">
            <templateId root="2.16.840.1.113883.10.20.22.4.27" extension="2014-06-09"/>
            <!-- Result observation template -->
            <id root="c7e81718-fdfe-436a-8540-16807f75caed"/>
        <code  code="72514-3" codeSystem="2.16.840.1.113883.6.1" displayName="Pain severity - 0-10 verbal numeric rating [Score] - Reported">
          <originalText><reference value="#observations-desc-19"/></originalText>
          <translation code="72514-3" codeSystem="2.16.840.1.113883.6.1" displayName="Pain severity - 0-10 verbal numeric rating [Score] - Reported"/>
        </code>
            <text>
              <reference value="#observations-desc-19"/>
            </text>
            <statusCode code="completed"/>
            <effectiveTime value="20190822185616"/>
            <value xsi:type="PQ" value="0.1712335111552692" unit="{score}"/>
          </observation>
        </component>
        <component>
          <observation classCode="OBS" moodCode="EVN">
            <templateId root="2.16.840.1.113883.10.20.22.4.27" extension="2014-06-09"/>
            <!-- Result observation template -->
            <id root="88c14189-7f0b-4142-b404-9c769ef0cf70"/>
        <code  code="29463-7" codeSystem="2.16.840.1.113883.6.1" displayName="Body Weight">
          <originalText><reference value="#observations-desc-20"/></originalText>
          <translation code="29463-7" codeSystem="2.16.840.1.113883.6.1" displayName="Body Weight"/>
        </code>
            <text>
              <reference value="#observations-desc-20"/>
            </text>
            <statusCode code="completed"/>
            <effectiveTime value="20190822185616"/>
            <value xsi:type="PQ" value="3.8716454824715187" unit="kg"/>
          </observation>
        </component>
        <component>
          <observation classCode="OBS" moodCode="EVN">
            <templateId root="2.16.840.1.113883.10.20.22.4.27" extension="2014-06-09"/>
            <!-- Result observation template -->
            <id root="817d3979-613e-4766-a1cb-d97b1d683dfc"/>
        <code  code="77606-2" codeSystem="2.16.840.1.113883.6.1" displayName="Weight-for-length Per age and sex">
          <originalText><reference value="#observations-desc-21"/></originalText>
          <translation code="77606-2" codeSystem="2.16.840.1.113883.6.1" displayName="Weight-for-length Per age and sex"/>
        </code>
            <text>
              <reference value="#observations-desc-21"/>
            </text>
            <statusCode code="completed"/>
            <effectiveTime value="20190822185616"/>
            <value xsi:type="PQ" value="0.0000967033934186" unit="%"/>
          </observation>
        </component>
        <component>
          <observation classCode="OBS" moodCode="EVN">
            <templateId root="2.16.840.1.113883.10.20.22.4.27" extension="2014-06-09"/>
            <!-- Result observation template -->
            <id root="c4dbe3d5-f901-47a7-b273-3d5c3f01c1cd"/>
        <code  code="8462-4" codeSystem="2.16.840.1.113883.6.1" displayName="Diastolic Blood Pressure">
          <originalText><reference value="#observations-desc-22"/></originalText>
          <translation code="8462-4" codeSystem="2.16.840.1.113883.6.1" displayName="Diastolic Blood Pressure"/>
        </code>
            <text>
              <reference value="#observations-desc-22"/>
            </text>
            <statusCode code="completed"/>
            <effectiveTime value="20190822185616"/>
            <value xsi:type="PQ" value="75.77562511387183" unit="mm[Hg]"/>
          </observation>
        </component>
        <component>
          <observation classCode="OBS" moodCode="EVN">
            <templateId root="2.16.840.1.113883.10.20.22.4.27" extension="2014-06-09"/>
            <!-- Result observation template -->
            <id root="b8b2e187-de3e-4e41-bef5-bebca4578e16"/>
        <code  code="8480-6" codeSystem="2.16.840.1.113883.6.1" displayName="Systolic Blood Pressure">
          <originalText><reference value="#observations-desc-22"/></originalText>
          <translation code="8480-6" codeSystem="2.16.840.1.113883.6.1" displayName="Systolic Blood Pressure"/>
        </code>
            <text>
              <reference value="#observations-desc-22"/>
            </text>
            <statusCode code="completed"/>
            <effectiveTime value="20190822185616"/>
            <value xsi:type="PQ" value="112.06334606714353" unit="mm[Hg]"/>
          </observation>
        </component>
        <component>
          <observation classCode="OBS" moodCode="EVN">
            <templateId root="2.16.840.1.113883.10.20.22.4.27" extension="2014-06-09"/>
            <!-- Result observation template -->
            <id root="82b7cd5f-db77-4c06-a0b1-be36e90891de"/>
        <code  code="72166-2" codeSystem="2.16.840.1.113883.6.1" displayName="Tobacco smoking status NHIS">
          <originalText><reference value="#observations-desc-23"/></originalText>
          <translation code="72166-2" codeSystem="2.16.840.1.113883.6.1" displayName="Tobacco smoking status NHIS"/>
        </code>
            <text>
              <reference value="#observations-desc-23"/>
            </text>
            <statusCode code="completed"/>
            <effectiveTime value="20190822185616"/>
            <value xsi:type="ST">SNOMED-CT 266919005 Never smoker</value>
          </observation>
        </component>
      </organizer>
    </entry>
  </section>
</component>
<component>
  <!--Immunizations-->
  <section>
    <templateId root="2.16.840.1.113883.10.20.22.2.2" extension="2015-08-01"/>
    <!--Immunizations section template-->
    <code code="11369-6" codeSystem="2.16.840.1.113883.6.1" codeSystemName="LOINC" displayName="History of immunizations"/>
    <title>Immunizations</title>
<text>
  <table border="1" width="100%">
    <thead>
      <tr>
        <th>Start</th>
        <th>Stop</th>
        <th>Description</th>
        <th>Code</th>
      </tr>
    </thead>
    <tbody>
        <tr>
          <td>2019-07-18T18:56:16-04:00</td>
          <td></td>
          <td ID="immunizations-desc-1">Hep B, adolescent or pediatric</td>
          <td ID="immunizations-code-1">http://hl7.org/fhir/sid/cvx 08</td>
        </tr>
        <tr>
          <td>2019-08-22T18:56:16-04:00</td>
          <td></td>
          <td ID="immunizations-desc-2">Hep B, adolescent or pediatric</td>
          <td ID="immunizations-code-2">http://hl7.org/fhir/sid/cvx 08</td>
        </tr>
    </tbody>
  </table>
</text>
    <entry typeCode="DRIV">
      <substanceAdministration classCode="SBADM" moodCode="EVN" negationInd="false">
        <templateId root="2.16.840.1.113883.10.20.22.4.52"/>
        <!-- Medication activity template -->
        <id root="7faa601e-ed6b-429c-b410-b1f2d487b1b3"/>
        <code code='IMMUNIZ' codeSystem='2.16.840.1.113883.5.4' codeSystemName='ActCode'/>
        <text>
          <reference value="#immunizations-desc-1"/>
        </text>
        <statusCode code="completed"/>
        <effectiveTime value="20190718185616"/>
        <doseQuantity nullFlavor="UNK"/>
        <consumable>
          <manufacturedProduct classCode="MANU">
            <templateId root="2.16.840.1.113883.10.20.22.4.54"/>
            <!-- Product template -->
            <manufacturedMaterial>
        <code  code="08" codeSystem="2.16.840.1.113883.12.292" displayName="Hep B, adolescent or pediatric">
          <originalText><reference value="#immunizations-desc-1"/></originalText>
          <translation code="08" codeSystem="2.16.840.1.113883.12.292" displayName="Hep B, adolescent or pediatric"/>
        </code>
              <name>Hep B, adolescent or pediatric</name>
            </manufacturedMaterial>
          </manufacturedProduct>
        </consumable>
      </substanceAdministration>
    </entry>
    <entry typeCode="DRIV">
      <substanceAdministration classCode="SBADM" moodCode="EVN" negationInd="false">
        <templateId root="2.16.840.1.113883.10.20.22.4.52"/>
        <!-- Medication activity template -->
        <id root="5af320da-acf4-4862-96d6-6729bb49656a"/>
        <code code='IMMUNIZ' codeSystem='2.16.840.1.113883.5.4' codeSystemName='ActCode'/>
        <text>
          <reference value="#immunizations-desc-2"/>
        </text>
        <statusCode code="completed"/>
        <effectiveTime value="20190822185616"/>
        <doseQuantity nullFlavor="UNK"/>
        <consumable>
          <manufacturedProduct classCode="MANU">
            <templateId root="2.16.840.1.113883.10.20.22.4.54"/>
            <!-- Product template -->
            <manufacturedMaterial>
        <code  code="08" codeSystem="2.16.840.1.113883.12.292" displayName="Hep B, adolescent or pediatric">
          <originalText><reference value="#immunizations-desc-2"/></originalText>
          <translation code="08" codeSystem="2.16.840.1.113883.12.292" displayName="Hep B, adolescent or pediatric"/>
        </code>
              <name>Hep B, adolescent or pediatric</name>
            </manufacturedMaterial>
          </manufacturedProduct>
        </consumable>
      </substanceAdministration>
    </entry>
  </section>
</component>
<component>
  <!-- Imaging Studies: patient has no imaging studies -->
  <section nullFlavor="NI">
    <templateId root="2.16.840.1.113883.10.20.22.1.5"/>
    <code code="18748-4" codeSystem="2.16.840.1.113883.6.1" codeSystemName="LOINC" displayName="Diagnostic Imaging Report"/>
    <title>Imaging Studies</title>
    <text>There are no current imaging studies at the time of this document's creation.</text>
  </section>
</component>
<component>
  <!--Social History - CCDA-->
  <section>
    <templateId root="2.16.840.1.113883.10.20.22.2.17" extension="2015-08-01"/>
    <!-- Social history section template -->
    <code code="29762-2" codeSystem="2.16.840.1.113883.6.1"/>
    <title>Social History</title>
    <text>There is no current social history at the time of this document's creation.</text>
  </section>
</component>
    </structuredBody>
  </component>
</ClinicalDocument>

